{
    "noiseTextureQuality": 3,
    "noiseLayers": [
        {
            "renderSettings": {
                "noiseType": 5,
                "scale": {
                    "x": 18.0,
                    "y": 23.0
                },
                "octaves": 5,
                "octaveScale": 2.0,
                "octaveMultiplier": 0.25,
                "tile": 1
            },
            "procedural": true,
            "noiseTexture": {
                "instanceID": 0
            }
        },
        {
            "renderSettings": {
                "noiseType": 6,
                "scale": {
                    "x": 8.0,
                    "y": 8.0
                },
                "octaves": 7,
                "octaveScale": 2.0,
                "octaveMultiplier": 0.5,
                "tile": 18
            },
            "procedural": true,
            "noiseTexture": {
                "instanceID": 0
            }
        },
        {
            "renderSettings": {
                "noiseType": 6,
                "scale": {
                    "x": 8.0,
                    "y": 8.0
                },
                "octaves": 3,
                "octaveScale": 2.0,
                "octaveMultiplier": 0.5,
                "tile": 168
            },
            "procedural": true,
            "noiseTexture": {
                "instanceID": 0
            }
        },
        {
            "renderSettings": {
                "noiseType": 4,
                "scale": {
                    "x": 8.0,
                    "y": 8.0
                },
                "octaves": 4,
                "octaveScale": 2.0,
                "octaveMultiplier": 0.6499999761581421,
                "tile": 256
            },
            "procedural": true,
            "noiseTexture": {
                "instanceID": 0
            }
        },
        {
            "renderSettings": {
                "noiseType": 2,
                "scale": {
                    "x": 16.0,
                    "y": 16.0
                },
                "octaves": 4,
                "octaveScale": 2.0,
                "octaveMultiplier": 0.5,
                "tile": 1
            },
            "procedural": true,
            "noiseTexture": {
                "instanceID": 0
            }
        },
        {
            "renderSettings": {
                "noiseType": 7,
                "scale": {
                    "x": 8.0,
                    "y": 8.0
                },
                "octaves": 3,
                "octaveScale": 2.0,
                "octaveMultiplier": 0.30000001192092898,
                "tile": 128
            },
            "procedural": true,
            "noiseTexture": {
                "instanceID": 0
            }
        }
    ],
    "renderSettings": {
        "geometryType": 3,
        "geometryXExtent": {
            "x": -100000.0,
            "y": 100000.0
        },
        "geometryYExtent": {
            "x": 1750.0,
            "y": 4250.0
        },
        "geometryZExtent": {
            "x": -100000.0,
            "y": 100000.0
        },
        "geometryHeight": 0.0,
        "coverageIntensity": 0.7070000171661377,
        "structureIntensity": 0.0729999989271164,
        "structureMultiply": 0.0,
        "detailIntensity": 0.07999999821186066,
        "detailMultiply": 0.0,
        "baseWarpIntensity": 0.0,
        "detailWarpIntensity": 0.4129999876022339,
        "heightGradientBottom": {
            "x": 0.0,
            "y": 0.14000000059604646
        },
        "heightGradientTop": {
            "x": 0.800000011920929,
            "y": 1.0
        },
        "rounding": 7.289999961853027,
        "roundingShape": 4.110000133514404,
        "windSkew": {
            "x": 1.0,
            "y": 0.0
        },
        "coverageTile": 1,
        "baseTile": 18,
        "structureTile": 168,
        "detailTile": 256,
        "baseWarpTile": 1,
        "detailWarpTile": 128,
        "coverageOffset": {
            "x": -0.09000000357627869,
            "y": 0.0,
            "z": -0.07000000029802323
        },
        "baseOffset": {
            "x": 5.892327308654785,
            "y": 0.0,
            "z": 1.246482014656067
        },
        "structureOffset": {
            "x": 0.0,
            "y": 0.0,
            "z": 0.0
        },
        "detailOffset": {
            "x": 0.0,
            "y": 0.0,
            "z": 0.0
        },
        "baseWarpOffset": {
            "x": 0.0,
            "y": 0.0,
            "z": 0.0
        },
        "detailWarpOffset": {
            "x": 0.0,
            "y": 0.0,
            "z": 0.0
        },
        "density": 35000.0,
        "attenuationDistance": 10000.0,
        "attenuationBias": 30000.0,
        "rampUp": {
            "x": 0.0,
            "y": 0.0
        },
        "extinctionCoefficients": {
            "x": 0.000003999999989900971,
            "y": 0.000003999999989900971,
            "z": 0.000003999999989900971
        },
        "scatteringCoefficients": {
            "x": 0.000003999999989900971,
            "y": 0.000003999999989900971,
            "z": 0.000003999999989900971
        },
        "multipleScatteringAmount": 0.6669999957084656,
        "multipleScatteringBias": 0.12700000405311585,
        "multipleScatteringRampDown": 0.14499999582767487,
        "multipleScatteringRampDownShape": 7.0,
        "silverSpread": 0.10000000149011612,
        "silverIntensity": 1.0,
        "anisotropy": 0.289000004529953,
        "ambient": 0.0,
        "ambientHeightRange": {
            "x": 0.0,
            "y": 1.0
        },
        "ambientStrengthRange": {
            "x": 0.6539999842643738,
            "y": 1.3079999685287476
        },
        "selfShadowing": 1,
        "highQualityShadows": 0,
        "maxSelfShadowDistance": 5035.0,
        "lightPollutionDimmer": 1.0,
        "celShade": 0,
        "celShadeLightingBands": 0.6000000238418579,
        "celShadeTransmittanceBands": 1.0,
        "castShadows": 1,
        "apparentThickness": 0.0,
        "verticalProbabilityHeightRange": {
            "x": 0.05999999865889549,
            "y": 0.27000001072883608
        },
        "verticalProbabilityStrength": 0.699999988079071,
        "depthProbabilityHeightRange": {
            "x": 0.05999999865889549,
            "y": 0.6600000262260437
        },
        "depthProbabilityStrengthRange": {
            "x": 0.5,
            "y": 2.0
        },
        "depthProbabilityDensityMultiplier": 4.0,
        "depthProbabilityBias": 0.296999990940094,
        "depthProbabilityDetailIndex": 0,
        "maxShadowIntensity": 0.7148426175117493,
        "reprojectionFrames": 1,
        "useTemporalDenoising": 1,
        "temporalDenoisingRatio": 0.125,
        "coarseStepSize": 0.0,
        "detailStepSize": 0.0,
        "coarseStepRange": {
            "x": 32.0,
            "y": 64.0
        },
        "detailStepRange": {
            "x": 96.0,
            "y": 160.0
        },
        "stepDistanceRange": {
            "x": 125.0,
            "y": 15000.0
        },
        "flythroughStepRange": {
            "x": 8.0,
            "y": 512.0
        },
        "flythroughStepDistanceRange": {
            "x": 0.0,
            "y": 50000.0
        },
        "mediaZeroThreshold": 0.00009999999747378752,
        "transmittanceZeroThreshold": 0.00009999999747378752,
        "maxConsecutiveZeroSamples": 0
    }
}